listenclosely/__init__.py
listenclosely/admin.py
listenclosely/app.py
listenclosely/celery.py
listenclosely/conf.py
listenclosely/managers.py
listenclosely/models.py
listenclosely/tasks.py
listenclosely/migrations/0001_initial.py
listenclosely/migrations/__init__.py
listenclosely/services/__init__.py
listenclosely/services/base.py
listenclosely/services/console.py
listenclosely/services/dummy.py
listenclosely/services/exceptions.py
listenclosely/strategies/__init__.py
listenclosely/strategies/base.py
listenclosely/strategies/first_free.py
listenclosely-0.1.2.dist-info/DESCRIPTION.rst
listenclosely-0.1.2.dist-info/METADATA
listenclosely-0.1.2.dist-info/RECORD
listenclosely-0.1.2.dist-info/WHEEL
listenclosely-0.1.2.dist-info/metadata.json
listenclosely-0.1.2.dist-info/top_level.txt
