Metadata-Version: 2.0
Name: listenclosely
Version: 0.1.2
Summary: Listenclosely is a django-app that works as a middle man to connect instant messaging 
Home-page: https://github.com/jlmadurga/listenclosely
Author: Juan Madurga
Author-email: jlmadurga@gmail.com
License: BSD
Keywords: listenclosely
Platform: UNKNOWN
Classifier: Development Status :: 3 - Alpha
Classifier: Framework :: Django
Classifier: Framework :: Django :: 1.8
Classifier: Framework :: Django :: 1.9
Classifier: Intended Audience :: Developers
Classifier: License :: OSI Approved :: BSD License
Classifier: Natural Language :: English
Classifier: Programming Language :: Python :: 2
Classifier: Programming Language :: Python :: 2.7
Classifier: Programming Language :: Python :: 3
Classifier: Programming Language :: Python :: 3.3
Classifier: Programming Language :: Python :: 3.4
Classifier: Programming Language :: Python :: 3.5
Requires-Dist: celery (==3.1.19)
Requires-Dist: django (>=1.8)
Requires-Dist: django-fsm (==2.3.0)
Requires-Dist: gevent (==1.0.2)
